ochat/__init__.py
ochat/config/__init__.py
ochat/config/conversation_template.py
ochat/config/model_config.py
ochat/data/generate_dataset.py
ochat/evaluation/README.md
ochat/evaluation/conv_eval.py
ochat/evaluation/convert_to_evalplus.py
ochat/evaluation/match_answer.py
ochat/evaluation/run_eval.py
ochat/evaluation/view_results.py
ochat/evaluation/eval_data/coding/humaneval/humaneval.jsonl
ochat/evaluation/eval_data/fs_cothub/bbh/boolean_expressions.jsonl
ochat/evaluation/eval_data/fs_cothub/bbh/causal_judgement.jsonl
ochat/evaluation/eval_data/fs_cothub/bbh/date_understanding.jsonl
ochat/evaluation/eval_data/fs_cothub/bbh/disambiguation_qa.jsonl
ochat/evaluation/eval_data/fs_cothub/bbh/dyck_languages.jsonl
ochat/evaluation/eval_data/fs_cothub/bbh/formal_fallacies.jsonl
ochat/evaluation/eval_data/fs_cothub/bbh/geometric_shapes.jsonl
ochat/evaluation/eval_data/fs_cothub/bbh/hyperbaton.jsonl
ochat/evaluation/eval_data/fs_cothub/bbh/logical_deduction_five_objects.jsonl
ochat/evaluation/eval_data/fs_cothub/bbh/logical_deduction_seven_objects.jsonl
ochat/evaluation/eval_data/fs_cothub/bbh/logical_deduction_three_objects.jsonl
ochat/evaluation/eval_data/fs_cothub/bbh/movie_recommendation.jsonl
ochat/evaluation/eval_data/fs_cothub/bbh/multistep_arithmetic_two.jsonl
ochat/evaluation/eval_data/fs_cothub/bbh/navigate.jsonl
ochat/evaluation/eval_data/fs_cothub/bbh/object_counting.jsonl
ochat/evaluation/eval_data/fs_cothub/bbh/penguins_in_a_table.jsonl
ochat/evaluation/eval_data/fs_cothub/bbh/reasoning_about_colored_objects.jsonl
ochat/evaluation/eval_data/fs_cothub/bbh/ruin_names.jsonl
ochat/evaluation/eval_data/fs_cothub/bbh/salient_translation_error_detection.jsonl
ochat/evaluation/eval_data/fs_cothub/bbh/snarks.jsonl
ochat/evaluation/eval_data/fs_cothub/bbh/sports_understanding.jsonl
ochat/evaluation/eval_data/fs_cothub/bbh/temporal_sequences.jsonl
ochat/evaluation/eval_data/fs_cothub/bbh/tracking_shuffled_objects_five_objects.jsonl
ochat-3.6.0.dist-info/LICENSE
ochat-3.6.0.dist-info/METADATA
ochat-3.6.0.dist-info/WHEEL
ochat-3.6.0.dist-info/top_level.txt
ochat-3.6.0.dist-info/RECORD
