Metadata-Version: 2.1
Name: ochat
Version: 3.6.0
Summary: An efficient framework for training and serving top-tier, open-source conversational LLMs.
Project-URL: Homepage, https://github.com/imoneoi/openchat
Project-URL: Bug Tracker, https://github.com/imoneoi/openchat/issues
Classifier: Programming Language :: Python :: 3
Classifier: License :: OSI Approved :: Apache Software License
Requires-Python: >=3.8
License-File: LICENSE
Requires-Dist: beautifulsoup4
Requires-Dist: markdownify
Requires-Dist: pylatexenc
Requires-Dist: openai >=1
Requires-Dist: tenacity
Requires-Dist: tiktoken
Requires-Dist: tqdm
Requires-Dist: wandb
Requires-Dist: numba
Requires-Dist: datasets
Requires-Dist: orjson
Requires-Dist: torch
Requires-Dist: packaging
Requires-Dist: ninja
Requires-Dist: flash-attn
Requires-Dist: ray
Requires-Dist: sentencepiece
Requires-Dist: transformers >=4.40.1
Requires-Dist: accelerate
Requires-Dist: protobuf
Requires-Dist: fastapi
Requires-Dist: pydantic
Requires-Dist: shortuuid
Requires-Dist: uvicorn
Requires-Dist: vllm >=0.4.0
Requires-Dist: pytest
